{
  "name": "Question",
  "description": "An asset named Question",
  "plural": "Question",
  "base": "PersistedModel",
  "idInjection": false,
  "options": {
    "validateUpsert": true,
    "composer": {
      "type": "asset",
      "namespace": "io.mefy.extra",
      "name": "Question",
      "fqn": "io.mefy.extra.Question",
      "abstract": false
    }
  },
  "properties": {
    "$class": {
      "type": "string",
      "required": false,
      "description": "The class identifier for this type",
      "default": "io.mefy.extra.Question"
    },
    "QuestionId": {
      "type": "string",
      "id": true,
      "required": true,
      "description": "The instance identifier for this type",
      "defaultFn": "uuidv4"
    },
    "options": {
      "type": "QOptions",
      "required": false
    },
    "parentId": {
      "type": "any",
      "required": false,
      "description": "The identifier of an instance of parentId"
    },
    "isParent": {
      "type": "boolean",
      "required": false
    },
    "condition": {
      "type": "string",
      "required": false
    },
    "enabled": {
      "type": "string",
      "required": false
    },
    "groupId": {
      "type": "string",
      "required": false
    },
    "background": {
      "type": "string",
      "required": false
    },
    "questionType": {
      "type": "string",
      "required": false
    },
    "shortQuestion": {
      "type": "string",
      "required": false
    },
    "longQuestion": {
      "type": "string",
      "required": false
    }
  },
  "validations": [],
  "relations": {},
  "acls": [],
  "methods": {}
}
